LICENSE
MANIFEST.in
README.md
setup.py
test/test_cancer_driver_gene.py
test/test_epitope_prediction.py
test/test_manufacturability.py
test/test_mutant_protein_sequence.py
test/test_shell_script.py
test/testing_helpers.py
vaxrank/__init__.py
vaxrank/cli.py
vaxrank/core_logic.py
vaxrank/epitope_prediction.py
vaxrank/gene_pathway_check.py
vaxrank/logging.conf
vaxrank/manufacturability.py
vaxrank/mutant_protein_fragment.py
vaxrank/patient_info.py
vaxrank/reference_proteome.py
vaxrank/report.py
vaxrank/vaccine_peptide.py
vaxrank/vaxrank_results.py
vaxrank.egg-info/PKG-INFO
vaxrank.egg-info/SOURCES.txt
vaxrank.egg-info/dependency_links.txt
vaxrank.egg-info/entry_points.txt
vaxrank.egg-info/requires.txt
vaxrank.egg-info/top_level.txt
vaxrank/data/cancer-driver-genes.csv
vaxrank/data/cancer-driver-variants.csv
vaxrank/data/class1-mhc-presentation-pathway.csv
vaxrank/data/interferon-gamma-response.csv
vaxrank/templates/stylesheet.css
vaxrank/templates/template.html
vaxrank/templates/template.txt