Metadata-Version: 2.1
Name: vaxrank
Version: 1.3.0
Summary: Mutant peptide ranking for personalized cancer vaccines
Home-page: https://github.com/openvax/vaxrank
Author: Alex Rubinsteyn, Julia Kodysh
Author-email: alex@openvax.org, julia@openvax.org
License: http://www.apache.org/licenses/LICENSE-2.0.html
Platform: UNKNOWN
Classifier: Development Status :: 4 - Beta
Classifier: Environment :: Console
Classifier: Operating System :: OS Independent
Classifier: Intended Audience :: Science/Research
Classifier: License :: OSI Approved :: Apache Software License
Classifier: Programming Language :: Python
Classifier: Topic :: Scientific/Engineering :: Bio-Informatics
